<annotation>
	<folder></folder>
	<filename>IMG_20220420_233015_jpg.rf.319ea096d762c5dd8e4a18264df114ad.jpg</filename>
	<path>IMG_20220420_233015_jpg.rf.319ea096d762c5dd8e4a18264df114ad.jpg</path>
	<source>
		<database>roboflow.ai</database>
	</source>
	<size>
		<width>640</width>
		<height>640</height>
		<depth>3</depth>
	</size>
	<segmented>0</segmented>
	<object>
		<name>text_bubble</name>
		<pose>Unspecified</pose>
		<truncated>0</truncated>
		<difficult>0</difficult>
		<occluded>0</occluded>
		<bndbox>
			<xmin>197</xmin>
			<xmax>437</xmax>
			<ymin>347</ymin>
			<ymax>441</ymax>
		</bndbox>
	</object>
</annotation>
